pyflush/__init__.py
pyflush-0.1.0.dist-info/METADATA
pyflush-0.1.0.dist-info/WHEEL
pyflush-0.1.0.dist-info/top_level.txt
pyflush-0.1.0.dist-info/RECORD
