Metadata-Version: 2.1
Name: pyflush
Version: 0.1.0
Summary: A python library to remove content of a directory, or file in a safer manner. After running pyflush, it became much safer to delete the file/directory manually/programmatically.
Home-page: https://github.com/mr-ravin/pyflush
Author: Ravin Kumar
Author-email: mr.ravin_kumar@hotmail.com
License: UNKNOWN
Platform: UNKNOWN
Classifier: Programming Language :: Python :: 3
Classifier: License :: OSI Approved :: MIT License
Classifier: Operating System :: OS Independent
Requires-Python: >=3.0
